ephyviewer/__init__.py
ephyviewer/base.py
ephyviewer/dataframeview.py
ephyviewer/epochencoder.py
ephyviewer/epochviewer.py
ephyviewer/eventlist.py
ephyviewer/mainviewer.py
ephyviewer/myqt.py
ephyviewer/navigation.py
ephyviewer/scripts.py
ephyviewer/spectrogramviewer.py
ephyviewer/spiketrainviewer.py
ephyviewer/standalone.py
ephyviewer/timefreqviewer.py
ephyviewer/tools.py
ephyviewer/traceviewer.py
ephyviewer/version.py
ephyviewer/videoviewer.py
ephyviewer/datasource/__init__.py
ephyviewer/datasource/epochs.py
ephyviewer/datasource/events.py
ephyviewer/datasource/neosource.py
ephyviewer/datasource/signals.py
ephyviewer/datasource/sourcebase.py
ephyviewer/datasource/spikeinterfacesources.py
ephyviewer/datasource/spikes.py
ephyviewer/datasource/video.py
ephyviewer/icons/__init__.py
ephyviewer/icons/icons_PyQt5.py
ephyviewer/icons/icons_PySide2.py
ephyviewer/icons/icons_PySide6.py
ephyviewer/icons/make_resources.py
ephyviewer/tests/__init__.py
ephyviewer/tests/test_base.py
ephyviewer/tests/test_dataframeview.py
ephyviewer/tests/test_datasource.py
ephyviewer/tests/test_epochencoder.py
ephyviewer/tests/test_epochviewer.py
ephyviewer/tests/test_eventlist.py
ephyviewer/tests/test_mainviewer.py
ephyviewer/tests/test_navigation.py
ephyviewer/tests/test_neoviewer.py
ephyviewer/tests/test_resources.py
ephyviewer/tests/test_spectrogramviewer.py
ephyviewer/tests/test_spikeinterfaceviewer.py
ephyviewer/tests/test_spiketrainviewer.py
ephyviewer/tests/test_standalone.py
ephyviewer/tests/test_timefreqviewer.py
ephyviewer/tests/test_traceviewer.py
ephyviewer/tests/test_videoviewer.py
ephyviewer/tests/testing_tools.py
ephyviewer-1.7.0.dist-info/LICENSE
ephyviewer-1.7.0.dist-info/METADATA
ephyviewer-1.7.0.dist-info/WHEEL
ephyviewer-1.7.0.dist-info/entry_points.txt
ephyviewer-1.7.0.dist-info/top_level.txt
ephyviewer-1.7.0.dist-info/RECORD
