Metadata-Version: 2.1
Name: ephyviewer
Version: 1.7.0
Summary: Simple viewers for ephys signals, events, video and more
Home-page: https://github.com/NeuralEnsemble/ephyviewer
Author: S.Garcia, Jeffrey Gill
Author-email: 
License: MIT
Project-URL: Documentation, https://ephyviewer.readthedocs.io/en/latest/
Project-URL: Source code, https://github.com/NeuralEnsemble/ephyviewer/
Project-URL: Bug tracker, https://github.com/NeuralEnsemble/ephyviewer/issues
Project-URL: Change log, https://ephyviewer.readthedocs.io/en/latest/releasenotes.html
Platform: UNKNOWN
Classifier: Intended Audience :: Science/Research
Classifier: License :: OSI Approved :: MIT License
Classifier: Natural Language :: English
Classifier: Operating System :: OS Independent
Classifier: Programming Language :: Python :: 3
License-File: LICENSE
Requires-Dist: matplotlib >=2.0
Requires-Dist: numpy
Requires-Dist: pyqtgraph >=0.10.0
Requires-Dist: scipy
Provides-Extra: docs
Requires-Dist: sphinx <2 ; extra == 'docs'
Requires-Dist: jinja2 <3.1.0 ; extra == 'docs'
Provides-Extra: tests
Requires-Dist: av ; extra == 'tests'
Requires-Dist: coveralls ; extra == 'tests'
Requires-Dist: neo >=0.10.0 ; extra == 'tests'
Requires-Dist: spikeinterface >=0.90.1 ; extra == 'tests'
Requires-Dist: pandas ; extra == 'tests'
Requires-Dist: pytest ; extra == 'tests'
Requires-Dist: pytest-cov ; extra == 'tests'
